q2googledrive/__init__.py
q2googledrive/q2googledrive.py
q2googledrive/version.py
q2googledrive-0.1.6.dist-info/METADATA
q2googledrive-0.1.6.dist-info/WHEEL
q2googledrive-0.1.6.dist-info/RECORD
