Metadata-Version: 2.1
Name: q2googledrive
Version: 0.1.6
Summary: 
Author: Andrei Puchko
Author-email: andrei.puchko@gmx.de
Requires-Python: >=3.8.1
Classifier: Programming Language :: Python :: 3
Classifier: Programming Language :: Python :: 3.9
Classifier: Programming Language :: Python :: 3.10
Classifier: Programming Language :: Python :: 3.11
Requires-Dist: google-api-python-client (>=2.120.0,<3.0.0)
Requires-Dist: google-auth-httplib2 (>=0.2.0,<0.3.0)
Requires-Dist: google-auth-oauthlib (>=1.2.0,<2.0.0)
Requires-Dist: gspread (>=6.0.2,<7.0.0)
